Metadata-Version: 2.1
Name: viecry
Version: 0.1
Summary: Password encryption
Home-page: https://github.com/ftonioloviemar/viecry
Download-URL: https://github.com/ftonioloviemar/viecry/archive/refs/tags/v_0.1.tar.gz
Author: Fabio Toniolo Vieira Junior
Author-email: ftoniolo@viemar.com.br
License: MIT
Keywords: viemar,password,cryptography
Classifier: Development Status :: 3 - Alpha
Classifier: Intended Audience :: Developers
Classifier: Topic :: Software Development :: Build Tools
Classifier: License :: OSI Approved :: MIT License
Classifier: Programming Language :: Python :: 3.0
Classifier: Programming Language :: Python :: 3.1
Classifier: Programming Language :: Python :: 3.2
Classifier: Programming Language :: Python :: 3.3
Classifier: Programming Language :: Python :: 3.4
Classifier: Programming Language :: Python :: 3.5
Classifier: Programming Language :: Python :: 3.6
Classifier: Programming Language :: Python :: 3.7
Classifier: Programming Language :: Python :: 3.8
Classifier: Programming Language :: Python :: 3.9
Classifier: Programming Language :: Python :: 3.10
Classifier: Programming Language :: Python :: 3.11
Classifier: Programming Language :: Python :: 3.12
License-File: LICENSE.txt
